slurm_job_resource_monitor/__init__.py
slurm_job_resource_monitor/_version.py
slurm_job_resource_monitor/job_monitor.py
slurm_job_resource_monitor-2.7.1.dist-info/LICENSE
slurm_job_resource_monitor-2.7.1.dist-info/METADATA
slurm_job_resource_monitor-2.7.1.dist-info/WHEEL
slurm_job_resource_monitor-2.7.1.dist-info/entry_points.txt
slurm_job_resource_monitor-2.7.1.dist-info/top_level.txt
slurm_job_resource_monitor-2.7.1.dist-info/RECORD
