Metadata-Version: 2.1
Name: slurm-job-resource-monitor
Version: 2.7.1
Summary: Command line tool for monitoring slurm jobs on a linux system.
Author-email: Tobias Schanz <tobias.machnitzki@hereon.de>
Project-URL: Homepage, https://github.com/tmachnitzki/slurm_job_resource_monitor
Project-URL: Bug Tracker, https://github.com/tmachnitzki/slurm_job_resource_monitor/issues
Classifier: Development Status :: 5 - Production/Stable
Classifier: Operating System :: POSIX :: Linux
Requires-Python: >=3.9
License-File: LICENSE
Requires-Dist: pandas
Requires-Dist: paramiko
Requires-Dist: rich
